LICENSE.txt
README.md
requirements.txt
setup.py
srfp/__init__.py
srfp/comms.py
srfp/filesystem.py
srfp/installer.py
srfp/protocol.py
srfp/test.py
srfp.egg-info/PKG-INFO
srfp.egg-info/SOURCES.txt
srfp.egg-info/dependency_links.txt
srfp.egg-info/entry_points.txt
srfp.egg-info/requires.txt
srfp.egg-info/top_level.txt
srfp/demos/__init__.py
srfp/demos/console.py
srfp/demos/tree.py