Metadata-Version: 1.1
Name: srfp
Version: 0.1.0
Summary: Client for the Simple Read-only File Protocol
Home-page: https://github.com/srfp-preservation/client
Author: Adam Brenecki
Author-email: adam@brenecki.id.au
License: UNKNOWN
Platform: UNKNOWN
Classifier: Development Status :: 4 - Beta
Classifier: Environment :: Console
Classifier: Intended Audience :: End Users/Desktop
Classifier: Intended Audience :: Information Technology
Classifier: Intended Audience :: Science/Research
Classifier: License :: OSI Approved :: GNU Affero General Public License v3 or later (AGPLv3+)
Classifier: Natural Language :: English
Classifier: Operating System :: OS Independent
Classifier: Topic :: Communications :: File Sharing
Classifier: Topic :: System :: Archiving
Classifier: Topic :: System :: Filesystems
